{
    "SOL": {
        "Name": "Solana",
        "Current_Price": 86.2,
        "Market_Cap_Rank": 7,
        "Dilution_Health": "100.0%",
        "Metcalfe_Activity_Score": 7.38,
        "Final_Speculative_Value": 92.5623,
        "Last_Updated": "2026-03-12 22:46"
    },
    "SUI": {
        "Name": "Sui",
        "Current_Price": 0.977423,
        "Market_Cap_Rank": 29,
        "Dilution_Health": "39.0%",
        "Metcalfe_Activity_Score": 11.12,
        "Final_Speculative_Value": 0.4236,
        "Last_Updated": "2026-03-12 22:46"
    },
    "SHIB": {
        "Name": "Shiba Inu",
        "Current_Price": 5.88e-06,
        "Market_Cap_Rank": 30,
        "Dilution_Health": "99.96%",
        "Metcalfe_Activity_Score": 4.44,
        "Final_Speculative_Value": 0.0,
        "Last_Updated": "2026-03-12 22:46"
    },
    "SKY": {
        "Name": "Sky",
        "Current_Price": 0.080798,
        "Market_Cap_Rank": 46,
        "Dilution_Health": "98.23%",
        "Metcalfe_Activity_Score": 1.04,
        "Final_Speculative_Value": 0.0802,
        "Last_Updated": "2026-03-12 22:46"
    },
    "STABLE": {
        "Name": "\u200b\u200bStable",
        "Current_Price": 0.02887434,
        "Market_Cap_Rank": 89,
        "Dilution_Health": "20.81%",
        "Metcalfe_Activity_Score": 3.41,
        "Final_Speculative_Value": 0.0062,
        "Last_Updated": "2026-03-12 22:46"
    },
    "STX": {
        "Name": "Stacks",
        "Current_Price": 0.255086,
        "Market_Cap_Rank": 100,
        "Dilution_Health": "100.0%",
        "Metcalfe_Activity_Score": 1.81,
        "Final_Speculative_Value": 0.2597,
        "Last_Updated": "2026-03-12 22:46"
    },
    "SEI": {
        "Name": "Sei",
        "Current_Price": 0.064961,
        "Market_Cap_Rank": 107,
        "Dilution_Health": "67.33%",
        "Metcalfe_Activity_Score": 9.55,
        "Final_Speculative_Value": 0.0479,
        "Last_Updated": "2026-03-12 22:46"
    },
    "SIREN": {
        "Name": "Siren",
        "Current_Price": 0.564365,
        "Market_Cap_Rank": 112,
        "Dilution_Health": "100.0%",
        "Metcalfe_Activity_Score": 8.09,
        "Final_Speculative_Value": 0.61,
        "Last_Updated": "2026-03-12 22:46"
    },
    "SUN": {
        "Name": "Sun Token",
        "Current_Price": 0.0160138,
        "Market_Cap_Rank": 130,
        "Dilution_Health": "96.58%",
        "Metcalfe_Activity_Score": 7.44,
        "Final_Speculative_Value": 0.0166,
        "Last_Updated": "2026-03-12 22:46"
    },
    "SPX": {
        "Name": "SPX6900",
        "Current_Price": 0.308656,
        "Market_Cap_Rank": 137,
        "Dilution_Health": "100.0%",
        "Metcalfe_Activity_Score": 2.19,
        "Final_Speculative_Value": 0.3154,
        "Last_Updated": "2026-03-12 22:46"
    },
    "SYRUP": {
        "Name": "Maple Finance",
        "Current_Price": 0.244009,
        "Market_Cap_Rank": 139,
        "Dilution_Health": "95.15%",
        "Metcalfe_Activity_Score": 7.11,
        "Final_Speculative_Value": 0.2487,
        "Last_Updated": "2026-03-12 22:46"
    },
    "STRK": {
        "Name": "Starknet",
        "Current_Price": 0.04101017,
        "Market_Cap_Rank": 163,
        "Dilution_Health": "54.88%",
        "Metcalfe_Activity_Score": 8.44,
        "Final_Speculative_Value": 0.0244,
        "Last_Updated": "2026-03-12 22:46"
    },
    "SAND": {
        "Name": "The Sandbox",
        "Current_Price": 0.08253,
        "Market_Cap_Rank": 165,
        "Dilution_Health": "88.91%",
        "Metcalfe_Activity_Score": 7.32,
        "Final_Speculative_Value": 0.0788,
        "Last_Updated": "2026-03-12 22:46"
    },
    "S": {
        "Name": "Sonic",
        "Current_Price": 0.04261006,
        "Market_Cap_Rank": 203,
        "Dilution_Health": "97.41%",
        "Metcalfe_Activity_Score": 9.55,
        "Final_Speculative_Value": 0.0455,
        "Last_Updated": "2026-03-12 22:46"
    },
    "SATUSD": {
        "Name": "Satoshi Stablecoin",
        "Current_Price": 0.995269,
        "Market_Cap_Rank": 206,
        "Dilution_Health": "100.0%",
        "Metcalfe_Activity_Score": 0.0,
        "Final_Speculative_Value": 0.9953,
        "Last_Updated": "2026-03-12 22:46"
    },
    "SENT": {
        "Name": "Sentient",
        "Current_Price": 0.02174796,
        "Market_Cap_Rank": 207,
        "Dilution_Health": "21.07%",
        "Metcalfe_Activity_Score": 11.05,
        "Final_Speculative_Value": 0.0051,
        "Last_Updated": "2026-03-12 22:46"
    },
    "SFP": {
        "Name": "SafePal",
        "Current_Price": 0.277191,
        "Market_Cap_Rank": 216,
        "Dilution_Health": "100.0%",
        "Metcalfe_Activity_Score": 2.09,
        "Final_Speculative_Value": 0.283,
        "Last_Updated": "2026-03-12 22:46"
    },
    "SKR": {
        "Name": "Saakuru",
        "Current_Price": 0.0001946,
        "Market_Cap_Rank": 706,
        "Dilution_Health": "70.33%",
        "Metcalfe_Activity_Score": 0.0,
        "Final_Speculative_Value": 0.0001,
        "Last_Updated": "2026-03-12 22:46"
    },
    "SOSO": {
        "Name": "SoSoValue",
        "Current_Price": 0.36401,
        "Market_Cap_Rank": 247,
        "Dilution_Health": "31.2%",
        "Metcalfe_Activity_Score": 2.98,
        "Final_Speculative_Value": 0.117,
        "Last_Updated": "2026-03-12 22:46"
    },
    "SNX": {
        "Name": "Synthetix",
        "Current_Price": 0.312108,
        "Market_Cap_Rank": 258,
        "Dilution_Health": "99.88%",
        "Metcalfe_Activity_Score": 11.21,
        "Final_Speculative_Value": 0.3467,
        "Last_Updated": "2026-03-12 22:46"
    },
    "STAC": {
        "Name": "Securitize Tokenized AAA CLO Fund",
        "Current_Price": 1006.48,
        "Market_Cap_Rank": 261,
        "Dilution_Health": "100.0%",
        "Metcalfe_Activity_Score": 0.0,
        "Final_Speculative_Value": 1006.48,
        "Last_Updated": "2026-03-12 22:46"
    },
    "SHFL": {
        "Name": "Shuffle",
        "Current_Price": 0.238832,
        "Market_Cap_Rank": 288,
        "Dilution_Health": "41.57%",
        "Metcalfe_Activity_Score": 0.63,
        "Final_Speculative_Value": 0.0999,
        "Last_Updated": "2026-03-12 22:46"
    },
    "SN64": {
        "Name": "Chutes",
        "Current_Price": 20.3,
        "Market_Cap_Rank": 291,
        "Dilution_Health": "100.0%",
        "Metcalfe_Activity_Score": 2.91,
        "Final_Speculative_Value": 20.8899,
        "Last_Updated": "2026-03-12 22:46"
    },
    "SWOP": {
        "Name": "Swop",
        "Current_Price": 0.00821441,
        "Market_Cap_Rank": 313,
        "Dilution_Health": "100.0%",
        "Metcalfe_Activity_Score": 0.0,
        "Final_Speculative_Value": 0.0082,
        "Last_Updated": "2026-03-12 22:46"
    },
    "SIGN": {
        "Name": "Sign",
        "Current_Price": 0.04681604,
        "Market_Cap_Rank": 335,
        "Dilution_Health": "16.4%",
        "Metcalfe_Activity_Score": 52.88,
        "Final_Speculative_Value": 0.0117,
        "Last_Updated": "2026-03-12 22:46"
    },
    "SAFE": {
        "Name": "SAFEbit",
        "Current_Price": 0.052014,
        "Market_Cap_Rank": 826,
        "Dilution_Health": "37.94%",
        "Metcalfe_Activity_Score": 3.77,
        "Final_Speculative_Value": 0.0205,
        "Last_Updated": "2026-03-12 22:46"
    },
    "SUPER": {
        "Name": "SuperVerse",
        "Current_Price": 0.114594,
        "Market_Cap_Rank": 349,
        "Dilution_Health": "63.72%",
        "Metcalfe_Activity_Score": 6.85,
        "Final_Speculative_Value": 0.078,
        "Last_Updated": "2026-03-12 22:46"
    },
    "SAHARA": {
        "Name": "Sahara AI",
        "Current_Price": 0.02269102,
        "Market_Cap_Rank": 375,
        "Dilution_Health": "29.09%",
        "Metcalfe_Activity_Score": 15.38,
        "Final_Speculative_Value": 0.0076,
        "Last_Updated": "2026-03-12 22:46"
    },
    "SOON": {
        "Name": "SOON",
        "Current_Price": 0.14841,
        "Market_Cap_Rank": 378,
        "Dilution_Health": "43.93%",
        "Metcalfe_Activity_Score": 5.52,
        "Final_Speculative_Value": 0.0688,
        "Last_Updated": "2026-03-12 22:46"
    },
    "SUSHI": {
        "Name": "Sushi",
        "Current_Price": 0.208218,
        "Market_Cap_Rank": 410,
        "Dilution_Health": "94.9%",
        "Metcalfe_Activity_Score": 11.93,
        "Final_Speculative_Value": 0.2212,
        "Last_Updated": "2026-03-12 22:46"
    },
    "SPK": {
        "Name": "Spark",
        "Current_Price": 0.02305863,
        "Market_Cap_Rank": 411,
        "Dilution_Health": "24.66%",
        "Metcalfe_Activity_Score": 29.66,
        "Final_Speculative_Value": 0.0074,
        "Last_Updated": "2026-03-12 22:46"
    },
    "SXT": {
        "Name": "Space and Time",
        "Current_Price": 0.01871874,
        "Market_Cap_Rank": 415,
        "Dilution_Health": "59.27%",
        "Metcalfe_Activity_Score": 10.7,
        "Final_Speculative_Value": 0.0123,
        "Last_Updated": "2026-03-12 22:46"
    },
    "SC": {
        "Name": "Siacoin",
        "Current_Price": 0.00103167,
        "Market_Cap_Rank": 444,
        "Dilution_Health": "100.0%",
        "Metcalfe_Activity_Score": 8.2,
        "Final_Speculative_Value": 0.0011,
        "Last_Updated": "2026-03-12 22:46"
    },
    "SN120": {
        "Name": "affine",
        "Current_Price": 17.22,
        "Market_Cap_Rank": 483,
        "Dilution_Health": "100.0%",
        "Metcalfe_Activity_Score": 1.0,
        "Final_Speculative_Value": 17.3929,
        "Last_Updated": "2026-03-12 22:46"
    },
    "SKYAI": {
        "Name": "SkyAI",
        "Current_Price": 0.04227562,
        "Market_Cap_Rank": 501,
        "Dilution_Health": "100.0%",
        "Metcalfe_Activity_Score": 6.5,
        "Final_Speculative_Value": 0.045,
        "Last_Updated": "2026-03-12 22:46"
    },
    "SN4": {
        "Name": "Targon",
        "Current_Price": 9.73,
        "Market_Cap_Rank": 506,
        "Dilution_Health": "100.0%",
        "Metcalfe_Activity_Score": 1.37,
        "Final_Speculative_Value": 9.8629,
        "Last_Updated": "2026-03-12 22:46"
    },
    "SSV": {
        "Name": "SSV Network",
        "Current_Price": 2.8,
        "Market_Cap_Rank": 515,
        "Dilution_Health": "100.0%",
        "Metcalfe_Activity_Score": 23.03,
        "Final_Speculative_Value": 3.4447,
        "Last_Updated": "2026-03-12 22:46"
    },
    "SN3": {
        "Name": "\u03c4emplar",
        "Current_Price": 9.69,
        "Market_Cap_Rank": 517,
        "Dilution_Health": "100.0%",
        "Metcalfe_Activity_Score": 10.5,
        "Final_Speculative_Value": 10.7074,
        "Last_Updated": "2026-03-12 22:46"
    },
    "SKL": {
        "Name": "SKALE",
        "Current_Price": 0.00664196,
        "Market_Cap_Rank": 524,
        "Dilution_Health": "99.77%",
        "Metcalfe_Activity_Score": 9.7,
        "Final_Speculative_Value": 0.0073,
        "Last_Updated": "2026-03-12 22:46"
    },
    "SRX": {
        "Name": "StorX",
        "Current_Price": 0.065747,
        "Market_Cap_Rank": 528,
        "Dilution_Health": "100.0%",
        "Metcalfe_Activity_Score": 5.76,
        "Final_Speculative_Value": 0.0695,
        "Last_Updated": "2026-03-12 22:46"
    },
    "STG": {
        "Name": "Stargate Finance",
        "Current_Price": 0.187829,
        "Market_Cap_Rank": 534,
        "Dilution_Health": "100.0%",
        "Metcalfe_Activity_Score": 10.91,
        "Final_Speculative_Value": 0.2083,
        "Last_Updated": "2026-03-12 22:46"
    },
    "SNT": {
        "Name": "Status",
        "Current_Price": 0.00956652,
        "Market_Cap_Rank": 554,
        "Dilution_Health": "58.2%",
        "Metcalfe_Activity_Score": 3.38,
        "Final_Speculative_Value": 0.0058,
        "Last_Updated": "2026-03-12 22:46"
    },
    "SNEK": {
        "Name": "Snek",
        "Current_Price": 0.00050504,
        "Market_Cap_Rank": 555,
        "Dilution_Health": "99.32%",
        "Metcalfe_Activity_Score": 4.12,
        "Final_Speculative_Value": 0.0005,
        "Last_Updated": "2026-03-12 22:46"
    },
    "SQD": {
        "Name": "SQD",
        "Current_Price": 0.03683694,
        "Market_Cap_Rank": 557,
        "Dilution_Health": "76.24%",
        "Metcalfe_Activity_Score": 4.17,
        "Final_Speculative_Value": 0.0293,
        "Last_Updated": "2026-03-12 22:46"
    },
    "SB": {
        "Name": "Snowbank",
        "Current_Price": 224.88,
        "Market_Cap_Rank": 567,
        "Dilution_Health": "100.0%",
        "Metcalfe_Activity_Score": 0.0,
        "Final_Speculative_Value": 224.8802,
        "Last_Updated": "2026-03-12 22:46"
    },
    "SLVON": {
        "Name": "iShares Silver Trust (Ondo Tokenized Stock)",
        "Current_Price": 76.14,
        "Market_Cap_Rank": 578,
        "Dilution_Health": "99.81%",
        "Metcalfe_Activity_Score": 15.8,
        "Final_Speculative_Value": 87.9988,
        "Last_Updated": "2026-03-12 22:46"
    },
    "SN62": {
        "Name": "Ridges AI",
        "Current_Price": 8.05,
        "Market_Cap_Rank": 579,
        "Dilution_Health": "100.0%",
        "Metcalfe_Activity_Score": 5.83,
        "Final_Speculative_Value": 8.519,
        "Last_Updated": "2026-03-12 22:46"
    },
    "SINGULARRY": {
        "Name": "Singularry",
        "Current_Price": 0.03465552,
        "Market_Cap_Rank": 583,
        "Dilution_Health": "100.0%",
        "Metcalfe_Activity_Score": 0.4,
        "Final_Speculative_Value": 0.0348,
        "Last_Updated": "2026-03-12 22:46"
    },
    "SWFTC": {
        "Name": "SWFTCOIN",
        "Current_Price": 0.00344021,
        "Market_Cap_Rank": 585,
        "Dilution_Health": "100.0%",
        "Metcalfe_Activity_Score": 0.91,
        "Final_Speculative_Value": 0.0035,
        "Last_Updated": "2026-03-12 22:46"
    },
    "SN8": {
        "Name": "Proprietary Trading Network",
        "Current_Price": 8.05,
        "Market_Cap_Rank": 588,
        "Dilution_Health": "100.0%",
        "Metcalfe_Activity_Score": 0.96,
        "Final_Speculative_Value": 8.1273,
        "Last_Updated": "2026-03-12 22:46"
    },
    "SN51": {
        "Name": "lium",
        "Current_Price": 8.82,
        "Market_Cap_Rank": 600,
        "Dilution_Health": "100.0%",
        "Metcalfe_Activity_Score": 0.28,
        "Final_Speculative_Value": 8.8446,
        "Last_Updated": "2026-03-12 22:46"
    },
    "SPYON": {
        "Name": "SPDR S&P 500 ETF (Ondo Tokenized ETF)",
        "Current_Price": 670.36,
        "Market_Cap_Rank": 610,
        "Dilution_Health": "100.04%",
        "Metcalfe_Activity_Score": 9.09,
        "Final_Speculative_Value": 731.595,
        "Last_Updated": "2026-03-12 22:46"
    },
    "STEEM": {
        "Name": "Steem",
        "Current_Price": 0.059432,
        "Market_Cap_Rank": 611,
        "Dilution_Health": "99.96%",
        "Metcalfe_Activity_Score": 58.52,
        "Final_Speculative_Value": 0.0942,
        "Last_Updated": "2026-03-12 22:46"
    },
    "SOMI": {
        "Name": "Somnia",
        "Current_Price": 0.188544,
        "Market_Cap_Rank": 637,
        "Dilution_Health": "16.02%",
        "Metcalfe_Activity_Score": 16.32,
        "Final_Speculative_Value": 0.0351,
        "Last_Updated": "2026-03-12 22:46"
    },
    "SPELL": {
        "Name": "Spell",
        "Current_Price": 0.00017337,
        "Market_Cap_Rank": 639,
        "Dilution_Health": "87.5%",
        "Metcalfe_Activity_Score": 10.91,
        "Final_Speculative_Value": 0.0002,
        "Last_Updated": "2026-03-12 22:46"
    },
    "SN75": {
        "Name": "Hippius",
        "Current_Price": 7.72,
        "Market_Cap_Rank": 646,
        "Dilution_Health": "100.0%",
        "Metcalfe_Activity_Score": 2.04,
        "Final_Speculative_Value": 7.8774,
        "Last_Updated": "2026-03-12 22:46"
    },
    "SVL": {
        "Name": "Slash Vision Labs",
        "Current_Price": 0.01545828,
        "Market_Cap_Rank": 647,
        "Dilution_Health": "19.0%",
        "Metcalfe_Activity_Score": 0.96,
        "Final_Speculative_Value": 0.003,
        "Last_Updated": "2026-03-12 22:46"
    },
    "SAI": {
        "Name": "Sai",
        "Current_Price": 10.84,
        "Market_Cap_Rank": 655,
        "Dilution_Health": "100.0%",
        "Metcalfe_Activity_Score": 0.0,
        "Final_Speculative_Value": 10.8402,
        "Last_Updated": "2026-03-12 22:46"
    },
    "STRAX": {
        "Name": "Xertra",
        "Current_Price": 0.01394843,
        "Market_Cap_Rank": 656,
        "Dilution_Health": "96.5%",
        "Metcalfe_Activity_Score": 1.27,
        "Final_Speculative_Value": 0.0136,
        "Last_Updated": "2026-03-12 22:46"
    },
    "SHX": {
        "Name": "Stronghold",
        "Current_Price": 0.0049427,
        "Market_Cap_Rank": 663,
        "Dilution_Health": "5.81%",
        "Metcalfe_Activity_Score": 1.43,
        "Final_Speculative_Value": 0.0003,
        "Last_Updated": "2026-03-12 22:46"
    },
    "SDEX": {
        "Name": "SMARDEX",
        "Current_Price": 0.00294954,
        "Market_Cap_Rank": 666,
        "Dilution_Health": "97.64%",
        "Metcalfe_Activity_Score": 1.0,
        "Final_Speculative_Value": 0.0029,
        "Last_Updated": "2026-03-12 22:46"
    },
    "SUSD": {
        "Name": "Synthetix sUSD",
        "Current_Price": 0.843062,
        "Market_Cap_Rank": 673,
        "Dilution_Health": "100.0%",
        "Metcalfe_Activity_Score": 0.83,
        "Final_Speculative_Value": 0.8501,
        "Last_Updated": "2026-03-12 22:46"
    },
    "SATS": {
        "Name": "SATS (Ordinals)",
        "Current_Price": 1.2964e-08,
        "Market_Cap_Rank": 689,
        "Dilution_Health": "100.0%",
        "Metcalfe_Activity_Score": 37.65,
        "Final_Speculative_Value": 0.0,
        "Last_Updated": "2026-03-12 22:46"
    },
    "SCRT": {
        "Name": "Secret",
        "Current_Price": 0.079051,
        "Market_Cap_Rank": 700,
        "Dilution_Health": "95.7%",
        "Metcalfe_Activity_Score": 5.93,
        "Final_Speculative_Value": 0.0801,
        "Last_Updated": "2026-03-12 22:46"
    },
    "SOPH": {
        "Name": "Sophon",
        "Current_Price": 0.00861713,
        "Market_Cap_Rank": 701,
        "Dilution_Health": "30.65%",
        "Metcalfe_Activity_Score": 8.46,
        "Final_Speculative_Value": 0.0029,
        "Last_Updated": "2026-03-12 22:46"
    },
    "SGB": {
        "Name": "Songbird",
        "Current_Price": 0.0015219,
        "Market_Cap_Rank": 723,
        "Dilution_Health": "86.71%",
        "Metcalfe_Activity_Score": 0.28,
        "Final_Speculative_Value": 0.0013,
        "Last_Updated": "2026-03-12 22:46"
    },
    "SN44": {
        "Name": "Score",
        "Current_Price": 5.94,
        "Market_Cap_Rank": 724,
        "Dilution_Health": "100.0%",
        "Metcalfe_Activity_Score": 6.81,
        "Final_Speculative_Value": 6.3447,
        "Last_Updated": "2026-03-12 22:46"
    },
    "SN9": {
        "Name": "iota",
        "Current_Price": 6.05,
        "Market_Cap_Rank": 749,
        "Dilution_Health": "100.0%",
        "Metcalfe_Activity_Score": 1.07,
        "Final_Speculative_Value": 6.1149,
        "Last_Updated": "2026-03-12 22:46"
    },
    "SOLVBTC.JUP": {
        "Name": "Solv Protocol SolvBTC Jupiter",
        "Current_Price": 87514,
        "Market_Cap_Rank": 761,
        "Dilution_Health": "100.0%",
        "Metcalfe_Activity_Score": 0.0,
        "Final_Speculative_Value": 87514.5417,
        "Last_Updated": "2026-03-12 22:46"
    },
    "SEDA": {
        "Name": "SEDA",
        "Current_Price": 0.02212903,
        "Market_Cap_Rank": 772,
        "Dilution_Health": "100.0%",
        "Metcalfe_Activity_Score": 1.55,
        "Final_Speculative_Value": 0.0225,
        "Last_Updated": "2026-03-12 22:46"
    },
    "SLP": {
        "Name": "Smooth Love Potion",
        "Current_Price": 0.00060299,
        "Market_Cap_Rank": 780,
        "Dilution_Health": "100.0%",
        "Metcalfe_Activity_Score": 19.34,
        "Final_Speculative_Value": 0.0007,
        "Last_Updated": "2026-03-12 22:46"
    },
    "SANTOS": {
        "Name": "Santos FC Fan Token",
        "Current_Price": 1.3,
        "Market_Cap_Rank": 800,
        "Dilution_Health": "53.65%",
        "Metcalfe_Activity_Score": 12.19,
        "Final_Speculative_Value": 0.7825,
        "Last_Updated": "2026-03-12 22:46"
    },
    "SYND": {
        "Name": "Syndicate",
        "Current_Price": 0.04297449,
        "Market_Cap_Rank": 811,
        "Dilution_Health": "47.87%",
        "Metcalfe_Activity_Score": 4.5,
        "Final_Speculative_Value": 0.0215,
        "Last_Updated": "2026-03-12 22:46"
    },
    "STRX": {
        "Name": "StrikeX",
        "Current_Price": 0.02327296,
        "Market_Cap_Rank": 819,
        "Dilution_Health": "95.62%",
        "Metcalfe_Activity_Score": 0.03,
        "Final_Speculative_Value": 0.0223,
        "Last_Updated": "2026-03-12 22:46"
    },
    "SAUCE": {
        "Name": "SaucerSwap",
        "Current_Price": 0.02211133,
        "Market_Cap_Rank": 829,
        "Dilution_Health": "88.92%",
        "Metcalfe_Activity_Score": 0.36,
        "Final_Speculative_Value": 0.0197,
        "Last_Updated": "2026-03-12 22:46"
    },
    "SAPIEN": {
        "Name": "Sapien",
        "Current_Price": 0.07832,
        "Market_Cap_Rank": 831,
        "Dilution_Health": "25.0%",
        "Metcalfe_Activity_Score": 22.72,
        "Final_Speculative_Value": 0.024,
        "Last_Updated": "2026-03-12 22:46"
    },
    "SN56": {
        "Name": "Gradients",
        "Current_Price": 4.71,
        "Market_Cap_Rank": 836,
        "Dilution_Health": "100.0%",
        "Metcalfe_Activity_Score": 4.15,
        "Final_Speculative_Value": 4.9055,
        "Last_Updated": "2026-03-12 22:46"
    },
    "SPYX": {
        "Name": "SP500 xStock",
        "Current_Price": 669.64,
        "Market_Cap_Rank": 854,
        "Dilution_Health": "13.97%",
        "Metcalfe_Activity_Score": 6.22,
        "Final_Speculative_Value": 99.344,
        "Last_Updated": "2026-03-12 22:46"
    },
    "SN39": {
        "Name": "basilica",
        "Current_Price": 4.93,
        "Market_Cap_Rank": 878,
        "Dilution_Health": "100.0%",
        "Metcalfe_Activity_Score": 7.72,
        "Final_Speculative_Value": 5.3104,
        "Last_Updated": "2026-03-12 22:46"
    },
    "STBL": {
        "Name": "STBL",
        "Current_Price": 0.03519337,
        "Market_Cap_Rank": 879,
        "Dilution_Health": "5.0%",
        "Metcalfe_Activity_Score": 16.96,
        "Final_Speculative_Value": 0.0021,
        "Last_Updated": "2026-03-12 22:46"
    },
    "SOSANA": {
        "Name": "SOSANA",
        "Current_Price": 0.19348,
        "Market_Cap_Rank": 891,
        "Dilution_Health": "100.0%",
        "Metcalfe_Activity_Score": 0.01,
        "Final_Speculative_Value": 0.1935,
        "Last_Updated": "2026-03-12 22:46"
    },
    "SOLO": {
        "Name": "Sologenic",
        "Current_Price": 0.04078231,
        "Market_Cap_Rank": 918,
        "Dilution_Health": "100.0%",
        "Metcalfe_Activity_Score": 0.16,
        "Final_Speculative_Value": 0.0408,
        "Last_Updated": "2026-03-12 22:46"
    },
    "SONIC": {
        "Name": "Sonic SVM",
        "Current_Price": 0.04327669,
        "Market_Cap_Rank": 936,
        "Dilution_Health": "15.0%",
        "Metcalfe_Activity_Score": 72.74,
        "Final_Speculative_Value": 0.0112,
        "Last_Updated": "2026-03-12 22:46"
    },
    "SPACE": {
        "Name": "Spacecoin",
        "Current_Price": 0.0071688,
        "Market_Cap_Rank": 941,
        "Dilution_Health": "10.25%",
        "Metcalfe_Activity_Score": 17.7,
        "Final_Speculative_Value": 0.0009,
        "Last_Updated": "2026-03-12 22:46"
    },
    "STO": {
        "Name": "StakeStone",
        "Current_Price": 0.066017,
        "Market_Cap_Rank": 956,
        "Dilution_Health": "22.53%",
        "Metcalfe_Activity_Score": 103.56,
        "Final_Speculative_Value": 0.0303,
        "Last_Updated": "2026-03-12 22:46"
    },
    "SN19": {
        "Name": "Nineteen.ai",
        "Current_Price": 3.63,
        "Market_Cap_Rank": 974,
        "Dilution_Health": "100.0%",
        "Metcalfe_Activity_Score": 5.72,
        "Final_Speculative_Value": 3.8378,
        "Last_Updated": "2026-03-12 22:46"
    },
    "SN81": {
        "Name": "grail",
        "Current_Price": 4.18,
        "Market_Cap_Rank": 985,
        "Dilution_Health": "100.0%",
        "Metcalfe_Activity_Score": 3.25,
        "Final_Speculative_Value": 4.3161,
        "Last_Updated": "2026-03-12 22:46"
    },
    "STORJ": {
        "Name": "Storj",
        "Current_Price": 0.095493,
        "Market_Cap_Rank": 991,
        "Dilution_Health": "33.83%",
        "Metcalfe_Activity_Score": 36.42,
        "Final_Speculative_Value": 0.0441,
        "Last_Updated": "2026-03-12 22:46"
    },
    "SPKCC": {
        "Name": "Spiko Digital Assets Cash & Carry Fund",
        "Current_Price": 1.012,
        "Market_Cap_Rank": 998,
        "Dilution_Health": "100.0%",
        "Metcalfe_Activity_Score": 0.0,
        "Final_Speculative_Value": 1.012,
        "Last_Updated": "2026-03-12 22:46"
    }
}