{
    "PYUSD": {
        "Name": "PayPal USD",
        "Current_Price": 0.999855,
        "Market_Cap_Rank": 25,
        "Dilution_Health": "100.0%",
        "Metcalfe_Activity_Score": 0.83,
        "Final_Speculative_Value": 1.0081,
        "10_Year_History": {},
        "5_Year_Forecast": {
            "2027": 1.1601,
            "2028": 1.3351,
            "2029": 1.5365,
            "2030": 1.7683,
            "2031": 2.035
        },
        "Last_Updated": "2026-03-08 01:21"
    },
    "PAXG": {
        "Name": "PAX Gold",
        "Current_Price": 5173.42,
        "Market_Cap_Rank": 37,
        "Dilution_Health": "100.0%",
        "Metcalfe_Activity_Score": 6.59,
        "Final_Speculative_Value": 5514.3648,
        "10_Year_History": {},
        "5_Year_Forecast": {
            "2027": 6377.8609,
            "2028": 7376.5722,
            "2029": 8531.672,
            "2030": 9867.6492,
            "2031": 11412.8275
        },
        "Last_Updated": "2026-03-08 01:21"
    },
    "PI": {
        "Name": "Pi Network",
        "Current_Price": 0.210058,
        "Market_Cap_Rank": 42,
        "Dilution_Health": "65.0%",
        "Metcalfe_Activity_Score": 4.12,
        "Final_Speculative_Value": 0.1422,
        "10_Year_History": {},
        "5_Year_Forecast": {
            "2027": 0.1641,
            "2028": 0.1894,
            "2029": 0.2186,
            "2030": 0.2523,
            "2031": 0.2912
        },
        "Last_Updated": "2026-03-08 01:21"
    },
    "PEPE": {
        "Name": "Pepe",
        "Current_Price": 3.24e-06,
        "Market_Cap_Rank": 55,
        "Dilution_Health": "100.0%",
        "Metcalfe_Activity_Score": 15.74,
        "Final_Speculative_Value": 0.0,
        "10_Year_History": {},
        "5_Year_Forecast": {
            "2027": 0.0,
            "2028": 0.0,
            "2029": 0.0,
            "2030": 0.0,
            "2031": 0.0
        },
        "Last_Updated": "2026-03-08 01:21"
    },
    "PUMP": {
        "Name": "Pump.fun",
        "Current_Price": 0.00188416,
        "Market_Cap_Rank": 61,
        "Dilution_Health": "59.0%",
        "Metcalfe_Activity_Score": 4.54,
        "Final_Speculative_Value": 0.0012,
        "10_Year_History": {},
        "5_Year_Forecast": {
            "2027": 0.0014,
            "2028": 0.0016,
            "2029": 0.0018,
            "2030": 0.0021,
            "2031": 0.0025
        },
        "Last_Updated": "2026-03-08 01:21"
    },
    "POL": {
        "Name": "POL (ex-MATIC)",
        "Current_Price": 0.094937,
        "Market_Cap_Rank": 65,
        "Dilution_Health": "100.0%",
        "Metcalfe_Activity_Score": 4.73,
        "Final_Speculative_Value": 0.0994,
        "10_Year_History": {},
        "5_Year_Forecast": {
            "2027": 0.1148,
            "2028": 0.1325,
            "2029": 0.153,
            "2030": 0.1767,
            "2031": 0.2041
        },
        "Last_Updated": "2026-03-08 01:21"
    },
    "PENGU": {
        "Name": "Pudgy Penguins",
        "Current_Price": 0.00655621,
        "Market_Cap_Rank": 109,
        "Dilution_Health": "78.79%",
        "Metcalfe_Activity_Score": 13.73,
        "Final_Speculative_Value": 0.0059,
        "10_Year_History": {},
        "5_Year_Forecast": {
            "2027": 0.0069,
            "2028": 0.008,
            "2029": 0.0093,
            "2030": 0.0108,
            "2031": 0.0126
        },
        "Last_Updated": "2026-03-08 01:21"
    },
    "PIPPIN": {
        "Name": "pippin",
        "Current_Price": 0.352827,
        "Market_Cap_Rank": 117,
        "Dilution_Health": "100.0%",
        "Metcalfe_Activity_Score": 5.38,
        "Final_Speculative_Value": 0.3718,
        "10_Year_History": {},
        "5_Year_Forecast": {
            "2027": 0.4296,
            "2028": 0.4963,
            "2029": 0.5734,
            "2030": 0.6625,
            "2031": 0.7655
        },
        "Last_Updated": "2026-03-08 01:21"
    },
    "PRIME": {
        "Name": "Echelon Prime",
        "Current_Price": 0.42699,
        "Market_Cap_Rank": 684,
        "Dilution_Health": "55.21%",
        "Metcalfe_Activity_Score": 10.36,
        "Final_Speculative_Value": 0.2602,
        "10_Year_History": {},
        "5_Year_Forecast": {
            "2027": 0.3019,
            "2028": 0.3503,
            "2029": 0.4065,
            "2030": 0.4717,
            "2031": 0.5474
        },
        "Last_Updated": "2026-03-08 01:21"
    },
    "PYTH": {
        "Name": "Pyth Network",
        "Current_Price": 0.04615575,
        "Market_Cap_Rank": 145,
        "Dilution_Health": "57.5%",
        "Metcalfe_Activity_Score": 2.95,
        "Final_Speculative_Value": 0.0273,
        "10_Year_History": {},
        "5_Year_Forecast": {
            "2027": 0.0315,
            "2028": 0.0363,
            "2029": 0.0418,
            "2030": 0.0482,
            "2031": 0.0556
        },
        "Last_Updated": "2026-03-08 01:21"
    },
    "PENDLE": {
        "Name": "Pendle",
        "Current_Price": 1.19,
        "Market_Cap_Rank": 173,
        "Dilution_Health": "58.78%",
        "Metcalfe_Activity_Score": 8.78,
        "Final_Speculative_Value": 0.7608,
        "10_Year_History": {},
        "5_Year_Forecast": {
            "2027": 0.8816,
            "2028": 1.0216,
            "2029": 1.1838,
            "2030": 1.3717,
            "2031": 1.5895
        },
        "Last_Updated": "2026-03-08 01:21"
    },
    "PC0000031": {
        "Name": "Tradable NA Rent Financing Platform SSTN",
        "Current_Price": 1.0,
        "Market_Cap_Rank": 175,
        "Dilution_Health": "100.0%",
        "Metcalfe_Activity_Score": 0.0,
        "Final_Speculative_Value": 1.0,
        "10_Year_History": {},
        "5_Year_Forecast": {
            "2027": 1.15,
            "2028": 1.3225,
            "2029": 1.5209,
            "2030": 1.749,
            "2031": 2.0114
        },
        "Last_Updated": "2026-03-08 01:21"
    },
    "PUSD": {
        "Name": "Pleasing USD",
        "Current_Price": 1.004,
        "Market_Cap_Rank": 232,
        "Dilution_Health": "100.0%",
        "Metcalfe_Activity_Score": 0.0,
        "Final_Speculative_Value": 1.004,
        "10_Year_History": {},
        "5_Year_Forecast": {
            "2027": 1.1546,
            "2028": 1.3278,
            "2029": 1.527,
            "2030": 1.756,
            "2031": 2.0194
        },
        "Last_Updated": "2026-03-08 01:21"
    },
    "PMUSD": {
        "Name": "Precious Metals USD",
        "Current_Price": 1.002,
        "Market_Cap_Rank": 251,
        "Dilution_Health": "100.0%",
        "Metcalfe_Activity_Score": 0.94,
        "Final_Speculative_Value": 1.0114,
        "10_Year_History": {},
        "5_Year_Forecast": {
            "2027": 1.1641,
            "2028": 1.3398,
            "2029": 1.542,
            "2030": 1.7747,
            "2031": 2.0426
        },
        "Last_Updated": "2026-03-08 01:21"
    },
    "PIEVERSE": {
        "Name": "Pieverse",
        "Current_Price": 0.515319,
        "Market_Cap_Rank": 257,
        "Dilution_Health": "20.5%",
        "Metcalfe_Activity_Score": 3.34,
        "Final_Speculative_Value": 0.1092,
        "10_Year_History": {},
        "5_Year_Forecast": {
            "2027": 0.1259,
            "2028": 0.1453,
            "2029": 0.1675,
            "2030": 0.1932,
            "2031": 0.2229
        },
        "Last_Updated": "2026-03-08 01:21"
    },
    "PC0000023": {
        "Name": "Tradable Singapore Fintech SSL",
        "Current_Price": 1.0,
        "Market_Cap_Rank": 262,
        "Dilution_Health": "88.08%",
        "Metcalfe_Activity_Score": 0.0,
        "Final_Speculative_Value": 0.8808,
        "10_Year_History": {},
        "5_Year_Forecast": {
            "2027": 1.0129,
            "2028": 1.1649,
            "2029": 1.3396,
            "2030": 1.5405,
            "2031": 1.7716
        },
        "Last_Updated": "2026-03-08 01:21"
    },
    "PGOLD": {
        "Name": "Pleasing Gold",
        "Current_Price": 5135.55,
        "Market_Cap_Rank": 265,
        "Dilution_Health": "100.0%",
        "Metcalfe_Activity_Score": 0.0,
        "Final_Speculative_Value": 5135.5509,
        "10_Year_History": {},
        "5_Year_Forecast": {
            "2027": 5905.8836,
            "2028": 6791.7663,
            "2029": 7810.5313,
            "2030": 8982.1112,
            "2031": 10329.428
        },
        "Last_Updated": "2026-03-08 01:21"
    },
    "PUFF": {
        "Name": "Puff The Dragon",
        "Current_Price": 0.07545,
        "Market_Cap_Rank": 359,
        "Dilution_Health": "100.0%",
        "Metcalfe_Activity_Score": 0.03,
        "Final_Speculative_Value": 0.0755,
        "10_Year_History": {},
        "5_Year_Forecast": {
            "2027": 0.0868,
            "2028": 0.0999,
            "2029": 0.1148,
            "2030": 0.1321,
            "2031": 0.1519
        },
        "Last_Updated": "2026-03-08 01:21"
    },
    "PYTHIA": {
        "Name": "PYTHIA",
        "Current_Price": 0.062027,
        "Market_Cap_Rank": 383,
        "Dilution_Health": "100.0%",
        "Metcalfe_Activity_Score": 2.27,
        "Final_Speculative_Value": 0.0634,
        "10_Year_History": {},
        "5_Year_Forecast": {
            "2027": 0.0731,
            "2028": 0.0842,
            "2029": 0.097,
            "2030": 0.1118,
            "2031": 0.1288
        },
        "Last_Updated": "2026-03-08 01:21"
    },
    "PLUME": {
        "Name": "Plume",
        "Current_Price": 0.01189211,
        "Market_Cap_Rank": 394,
        "Dilution_Health": "51.21%",
        "Metcalfe_Activity_Score": 62.61,
        "Final_Speculative_Value": 0.0099,
        "10_Year_History": {},
        "5_Year_Forecast": {
            "2027": 0.012,
            "2028": 0.0146,
            "2029": 0.0177,
            "2030": 0.0214,
            "2031": 0.026
        },
        "Last_Updated": "2026-03-08 01:21"
    },
    "PCI": {
        "Name": "Paycoin",
        "Current_Price": 0.054584,
        "Market_Cap_Rank": 413,
        "Dilution_Health": "53.82%",
        "Metcalfe_Activity_Score": 0.77,
        "Final_Speculative_Value": 0.0296,
        "10_Year_History": {},
        "5_Year_Forecast": {
            "2027": 0.0341,
            "2028": 0.0392,
            "2029": 0.0451,
            "2030": 0.0519,
            "2031": 0.0597
        },
        "Last_Updated": "2026-03-08 01:21"
    },
    "PROVE": {
        "Name": "Succinct",
        "Current_Price": 0.263004,
        "Market_Cap_Rank": 432,
        "Dilution_Health": "19.5%",
        "Metcalfe_Activity_Score": 14.96,
        "Final_Speculative_Value": 0.059,
        "10_Year_History": {},
        "5_Year_Forecast": {
            "2027": 0.0687,
            "2028": 0.0801,
            "2029": 0.0933,
            "2030": 0.1087,
            "2031": 0.1266
        },
        "Last_Updated": "2026-03-08 01:21"
    },
    "POLYX": {
        "Name": "Polymesh",
        "Current_Price": 0.04072535,
        "Market_Cap_Rank": 434,
        "Dilution_Health": "100.0%",
        "Metcalfe_Activity_Score": 3.87,
        "Final_Speculative_Value": 0.0423,
        "10_Year_History": {},
        "5_Year_Forecast": {
            "2027": 0.0488,
            "2028": 0.0563,
            "2029": 0.065,
            "2030": 0.075,
            "2031": 0.0865
        },
        "Last_Updated": "2026-03-08 01:21"
    },
    "POPCAT": {
        "Name": "Popcat",
        "Current_Price": 0.04884506,
        "Market_Cap_Rank": 452,
        "Dilution_Health": "100.0%",
        "Metcalfe_Activity_Score": 25.99,
        "Final_Speculative_Value": 0.0615,
        "10_Year_History": {},
        "5_Year_Forecast": {
            "2027": 0.0723,
            "2028": 0.0851,
            "2029": 0.1,
            "2030": 0.1176,
            "2031": 0.1383
        },
        "Last_Updated": "2026-03-08 01:21"
    },
    "PLLD": {
        "Name": "Palladium Network",
        "Current_Price": 0.925286,
        "Market_Cap_Rank": 455,
        "Dilution_Health": "98.08%",
        "Metcalfe_Activity_Score": 0.28,
        "Final_Speculative_Value": 0.91,
        "10_Year_History": {},
        "5_Year_Forecast": {
            "2027": 1.0468,
            "2028": 1.2041,
            "2029": 1.385,
            "2030": 1.5931,
            "2031": 1.8326
        },
        "Last_Updated": "2026-03-08 01:21"
    },
    "PNUT": {
        "Name": "Peanut the Squirrel",
        "Current_Price": 0.04408265,
        "Market_Cap_Rank": 478,
        "Dilution_Health": "100.0%",
        "Metcalfe_Activity_Score": 19.44,
        "Final_Speculative_Value": 0.0527,
        "10_Year_History": {},
        "5_Year_Forecast": {
            "2027": 0.0616,
            "2028": 0.0721,
            "2029": 0.0843,
            "2030": 0.0986,
            "2031": 0.1153
        },
        "Last_Updated": "2026-03-08 01:21"
    },
    "PTGC": {
        "Name": "The Grays Currency",
        "Current_Price": 0.00015077,
        "Market_Cap_Rank": 483,
        "Dilution_Health": "100.0%",
        "Metcalfe_Activity_Score": 0.1,
        "Final_Speculative_Value": 0.0002,
        "10_Year_History": {},
        "5_Year_Forecast": {
            "2027": 0.0002,
            "2028": 0.0003,
            "2029": 0.0003,
            "2030": 0.0003,
            "2031": 0.0004
        },
        "Last_Updated": "2026-03-08 01:21"
    },
    "PURR": {
        "Name": "Purr",
        "Current_Price": 0.070352,
        "Market_Cap_Rank": 495,
        "Dilution_Health": "100.0%",
        "Metcalfe_Activity_Score": 1.14,
        "Final_Speculative_Value": 0.0712,
        "10_Year_History": {},
        "5_Year_Forecast": {
            "2027": 0.082,
            "2028": 0.0943,
            "2029": 0.1086,
            "2030": 0.125,
            "2031": 0.1439
        },
        "Last_Updated": "2026-03-08 01:21"
    },
    "PUNDIX": {
        "Name": "Pundi X",
        "Current_Price": 0.147642,
        "Market_Cap_Rank": 527,
        "Dilution_Health": "100.0%",
        "Metcalfe_Activity_Score": 2.28,
        "Final_Speculative_Value": 0.151,
        "10_Year_History": {},
        "5_Year_Forecast": {
            "2027": 0.174,
            "2028": 0.2005,
            "2029": 0.231,
            "2030": 0.2662,
            "2031": 0.3067
        },
        "Last_Updated": "2026-03-08 01:21"
    },
    "PEOPLE": {
        "Name": "ConstitutionDAO",
        "Current_Price": 0.00679699,
        "Market_Cap_Rank": 565,
        "Dilution_Health": "100.0%",
        "Metcalfe_Activity_Score": 13.67,
        "Final_Speculative_Value": 0.0077,
        "10_Year_History": {},
        "5_Year_Forecast": {
            "2027": 0.009,
            "2028": 0.0104,
            "2029": 0.0121,
            "2030": 0.0141,
            "2031": 0.0164
        },
        "Last_Updated": "2026-03-08 01:21"
    },
    "POWR": {
        "Name": "Powerledger",
        "Current_Price": 0.064775,
        "Market_Cap_Rank": 567,
        "Dilution_Health": "53.0%",
        "Metcalfe_Activity_Score": 20.69,
        "Final_Speculative_Value": 0.0414,
        "10_Year_History": {},
        "5_Year_Forecast": {
            "2027": 0.0485,
            "2028": 0.0567,
            "2029": 0.0664,
            "2030": 0.0778,
            "2031": 0.091
        },
        "Last_Updated": "2026-03-08 01:21"
    },
    "PM": {
        "Name": "PumpMeme",
        "Current_Price": 1.072,
        "Market_Cap_Rank": 568,
        "Dilution_Health": "32.01%",
        "Metcalfe_Activity_Score": 0.44,
        "Final_Speculative_Value": 0.3447,
        "10_Year_History": {},
        "5_Year_Forecast": {
            "2027": 0.3966,
            "2028": 0.4562,
            "2029": 0.5249,
            "2030": 0.6038,
            "2031": 0.6947
        },
        "Last_Updated": "2026-03-08 01:21"
    },
    "POKT": {
        "Name": "Pocket Network",
        "Current_Price": 0.01534202,
        "Market_Cap_Rank": 613,
        "Dilution_Health": "85.55%",
        "Metcalfe_Activity_Score": 45.6,
        "Final_Speculative_Value": 0.0191,
        "10_Year_History": {},
        "5_Year_Forecast": {
            "2027": 0.0228,
            "2028": 0.0273,
            "2029": 0.0326,
            "2030": 0.039,
            "2031": 0.0467
        },
        "Last_Updated": "2026-03-08 01:21"
    },
    "PHA": {
        "Name": "PHALA",
        "Current_Price": 0.03458421,
        "Market_Cap_Rank": 641,
        "Dilution_Health": "83.16%",
        "Metcalfe_Activity_Score": 66.95,
        "Final_Speculative_Value": 0.048,
        "10_Year_History": {},
        "5_Year_Forecast": {
            "2027": 0.0584,
            "2028": 0.0711,
            "2029": 0.0865,
            "2030": 0.1053,
            "2031": 0.1281
        },
        "Last_Updated": "2026-03-08 01:21"
    },
    "PEAQ": {
        "Name": "peaq",
        "Current_Price": 0.01408153,
        "Market_Cap_Rank": 666,
        "Dilution_Health": "43.75%",
        "Metcalfe_Activity_Score": 4.74,
        "Final_Speculative_Value": 0.0065,
        "10_Year_History": {},
        "5_Year_Forecast": {
            "2027": 0.0075,
            "2028": 0.0087,
            "2029": 0.01,
            "2030": 0.0116,
            "2031": 0.0133
        },
        "Last_Updated": "2026-03-08 01:21"
    },
    "PRDT": {
        "Name": "Predictions",
        "Current_Price": 1.11,
        "Market_Cap_Rank": 672,
        "Dilution_Health": "40.0%",
        "Metcalfe_Activity_Score": 0.28,
        "Final_Speculative_Value": 0.4452,
        "10_Year_History": {},
        "5_Year_Forecast": {
            "2027": 0.5121,
            "2028": 0.5891,
            "2029": 0.6776,
            "2030": 0.7794,
            "2031": 0.8965
        },
        "Last_Updated": "2026-03-08 01:21"
    },
    "POWER": {
        "Name": "Power Protocol",
        "Current_Price": 0.115186,
        "Market_Cap_Rank": 726,
        "Dilution_Health": "21.0%",
        "Metcalfe_Activity_Score": 56.94,
        "Final_Speculative_Value": 0.038,
        "10_Year_History": {},
        "5_Year_Forecast": {
            "2027": 0.0459,
            "2028": 0.0554,
            "2029": 0.0668,
            "2030": 0.0806,
            "2031": 0.0973
        },
        "Last_Updated": "2026-03-08 01:21"
    },
    "PINKSALE": {
        "Name": "PinkSale",
        "Current_Price": 224.42,
        "Market_Cap_Rank": 755,
        "Dilution_Health": "100.0%",
        "Metcalfe_Activity_Score": 0.0,
        "Final_Speculative_Value": 224.4201,
        "10_Year_History": {},
        "5_Year_Forecast": {
            "2027": 258.0831,
            "2028": 296.7956,
            "2029": 341.315,
            "2030": 392.5122,
            "2031": 451.3891
        },
        "Last_Updated": "2026-03-08 01:21"
    },
    "PEP": {
        "Name": "Pepecoin",
        "Current_Price": 0.00020257,
        "Market_Cap_Rank": 791,
        "Dilution_Health": "100.0%",
        "Metcalfe_Activity_Score": 0.54,
        "Final_Speculative_Value": 0.0002,
        "10_Year_History": {},
        "5_Year_Forecast": {
            "2027": 0.0002,
            "2028": 0.0003,
            "2029": 0.0003,
            "2030": 0.0004,
            "2031": 0.0004
        },
        "Last_Updated": "2026-03-08 01:21"
    },
    "PRO": {
        "Name": "Propy",
        "Current_Price": 0.350525,
        "Market_Cap_Rank": 797,
        "Dilution_Health": "57.9%",
        "Metcalfe_Activity_Score": 15.13,
        "Final_Speculative_Value": 0.2337,
        "10_Year_History": {},
        "5_Year_Forecast": {
            "2027": 0.2723,
            "2028": 0.3173,
            "2029": 0.3696,
            "2030": 0.4307,
            "2031": 0.5018
        },
        "Last_Updated": "2026-03-08 01:21"
    },
    "PARTI": {
        "Name": "Particle Network",
        "Current_Price": 0.083999,
        "Market_Cap_Rank": 815,
        "Dilution_Health": "23.3%",
        "Metcalfe_Activity_Score": 41.7,
        "Final_Speculative_Value": 0.0277,
        "10_Year_History": {},
        "5_Year_Forecast": {
            "2027": 0.033,
            "2028": 0.0393,
            "2029": 0.0469,
            "2030": 0.0559,
            "2031": 0.0666
        },
        "Last_Updated": "2026-03-08 01:21"
    },
    "PYBOBO": {
        "Name": "Capybobo",
        "Current_Price": 0.000804,
        "Market_Cap_Rank": 823,
        "Dilution_Health": "23.89%",
        "Metcalfe_Activity_Score": 16.99,
        "Final_Speculative_Value": 0.0002,
        "10_Year_History": {},
        "5_Year_Forecast": {
            "2027": 0.0002,
            "2028": 0.0003,
            "2029": 0.0003,
            "2030": 0.0004,
            "2031": 0.0004
        },
        "Last_Updated": "2026-03-08 01:21"
    },
    "PROM": {
        "Name": "Prom",
        "Current_Price": 1.037,
        "Market_Cap_Rank": 829,
        "Dilution_Health": "94.81%",
        "Metcalfe_Activity_Score": 14.58,
        "Final_Speculative_Value": 1.1265,
        "10_Year_History": {},
        "5_Year_Forecast": {
            "2027": 1.3119,
            "2028": 1.5278,
            "2029": 1.7793,
            "2030": 2.0721,
            "2031": 2.4131
        },
        "Last_Updated": "2026-03-08 01:21"
    },
    "POND": {
        "Name": "Marlin",
        "Current_Price": 0.00227567,
        "Market_Cap_Rank": 836,
        "Dilution_Health": "82.02%",
        "Metcalfe_Activity_Score": 3.5,
        "Final_Speculative_Value": 0.0019,
        "10_Year_History": {},
        "5_Year_Forecast": {
            "2027": 0.0022,
            "2028": 0.0025,
            "2029": 0.0029,
            "2030": 0.0034,
            "2031": 0.0039
        },
        "Last_Updated": "2026-03-08 01:21"
    },
    "PONKE": {
        "Name": "PONKE",
        "Current_Price": 0.02870674,
        "Market_Cap_Rank": 903,
        "Dilution_Health": "99.99%",
        "Metcalfe_Activity_Score": 9.43,
        "Final_Speculative_Value": 0.0314,
        "10_Year_History": {},
        "5_Year_Forecast": {
            "2027": 0.0364,
            "2028": 0.0422,
            "2029": 0.0489,
            "2030": 0.0567,
            "2031": 0.0658
        },
        "Last_Updated": "2026-03-08 01:22"
    },
    "PCOCK": {
        "Name": "PulseChain Peacock",
        "Current_Price": 0.0183698,
        "Market_Cap_Rank": 908,
        "Dilution_Health": "100.0%",
        "Metcalfe_Activity_Score": 1.05,
        "Final_Speculative_Value": 0.0186,
        "10_Year_History": {},
        "5_Year_Forecast": {
            "2027": 0.0214,
            "2028": 0.0246,
            "2029": 0.0284,
            "2030": 0.0327,
            "2031": 0.0376
        },
        "Last_Updated": "2026-03-08 01:22"
    },
    "PAAL": {
        "Name": "PAAL AI",
        "Current_Price": 0.01630803,
        "Market_Cap_Rank": 930,
        "Dilution_Health": "89.75%",
        "Metcalfe_Activity_Score": 5.42,
        "Final_Speculative_Value": 0.0154,
        "10_Year_History": {},
        "5_Year_Forecast": {
            "2027": 0.0178,
            "2028": 0.0206,
            "2029": 0.0238,
            "2030": 0.0274,
            "2031": 0.0317
        },
        "Last_Updated": "2026-03-08 01:22"
    },
    "PNKSTR": {
        "Name": "PunkStrategy",
        "Current_Price": 0.01405214,
        "Market_Cap_Rank": 980,
        "Dilution_Health": "100.0%",
        "Metcalfe_Activity_Score": 3.12,
        "Final_Speculative_Value": 0.0145,
        "10_Year_History": {},
        "5_Year_Forecast": {
            "2027": 0.0167,
            "2028": 0.0193,
            "2029": 0.0222,
            "2030": 0.0256,
            "2031": 0.0296
        },
        "Last_Updated": "2026-03-08 01:22"
    }
}