{
    "WBT": {
        "Name": "WhiteBIT Coin",
        "Current_Price": 54.85,
        "Market_Cap": 11709611010.0,
        "Financial_Tab_Data": {
            "Economic_Activity": {
                "Volume": 97362009.0,
                "TVL": 0,
                "Fees": 0
            },
            "Supply": {
                "Circulating": 213480325.0,
                "Total": 319980325.0,
                "Locked_Pct": 33.28329640267725
            }
        },
        "Quality_Scores": {
            "Predictability": 7,
            "Profitability": 5,
            "Growth": 6,
            "Moat": 4,
            "Financial_Strength": 5,
            "Valuation": 7
        },
        "10_Year_History": {},
        "Last_Updated": "2026-03-09 18:30"
    },
    "WLFI": {
        "Name": "World Liberty Financial",
        "Current_Price": 0.100086,
        "Market_Cap": 2768228640.0,
        "Financial_Tab_Data": {
            "Economic_Activity": {
                "Volume": 71580956.0,
                "TVL": 0,
                "Fees": 0
            },
            "Supply": {
                "Circulating": 27661355458.0,
                "Total": 100000000000.0,
                "Locked_Pct": 72.33864454200001
            }
        },
        "Quality_Scores": {
            "Predictability": 7,
            "Profitability": 5,
            "Growth": 6,
            "Moat": 4,
            "Financial_Strength": 5,
            "Valuation": 7
        },
        "10_Year_History": {},
        "Last_Updated": "2026-03-09 18:30"
    },
    "WLD": {
        "Name": "Worldcoin",
        "Current_Price": 0.362601,
        "Market_Cap": 1054912595.0,
        "Financial_Tab_Data": {
            "Economic_Activity": {
                "Volume": 109582496.0,
                "TVL": 0,
                "Fees": 0
            },
            "Supply": {
                "Circulating": 2909575593.481728,
                "Total": 10000000000.0,
                "Locked_Pct": 70.90424406518272
            }
        },
        "Quality_Scores": {
            "Predictability": 7,
            "Profitability": 5,
            "Growth": 9,
            "Moat": 4,
            "Financial_Strength": 5,
            "Valuation": 7
        },
        "10_Year_History": {},
        "Last_Updated": "2026-03-09 18:30"
    },
    "WFI": {
        "Name": "WeFi",
        "Current_Price": 2.24,
        "Market_Cap": 181435638.0,
        "Financial_Tab_Data": {
            "Economic_Activity": {
                "Volume": 2788802.0,
                "TVL": 0,
                "Fees": 0
            },
            "Supply": {
                "Circulating": 81042230.77284977,
                "Total": 1000000000.0,
                "Locked_Pct": 91.89577692271502
            }
        },
        "Quality_Scores": {
            "Predictability": 7,
            "Profitability": 5,
            "Growth": 6,
            "Moat": 4,
            "Financial_Strength": 5,
            "Valuation": 7
        },
        "10_Year_History": {},
        "Last_Updated": "2026-03-09 18:32"
    },
    "WIF": {
        "Name": "dogwifhat",
        "Current_Price": 0.175508,
        "Market_Cap": 175416746.0,
        "Financial_Tab_Data": {
            "Economic_Activity": {
                "Volume": 92902338.0,
                "TVL": 0,
                "Fees": 0
            },
            "Supply": {
                "Circulating": 998926392.0,
                "Total": 998926392.0,
                "Locked_Pct": 0
            }
        },
        "Quality_Scores": {
            "Predictability": 7,
            "Profitability": 5,
            "Growth": 9,
            "Moat": 4,
            "Financial_Strength": 9,
            "Valuation": 7
        },
        "10_Year_History": {},
        "Last_Updated": "2026-03-09 18:32"
    },
    "WAL": {
        "Name": "Walrus",
        "Current_Price": 0.075695,
        "Market_Cap": 169722614.0,
        "Financial_Tab_Data": {
            "Economic_Activity": {
                "Volume": 7214356.0,
                "TVL": 0,
                "Fees": 0
            },
            "Supply": {
                "Circulating": 2242500000.0,
                "Total": 5000000000.0,
                "Locked_Pct": 55.15
            }
        },
        "Quality_Scores": {
            "Predictability": 7,
            "Profitability": 5,
            "Growth": 6,
            "Moat": 4,
            "Financial_Strength": 5,
            "Valuation": 7
        },
        "10_Year_History": {},
        "Last_Updated": "2026-03-09 18:32"
    },
    "WEMIX": {
        "Name": "WEMIX",
        "Current_Price": 0.289734,
        "Market_Cap": 133952580.0,
        "Financial_Tab_Data": {
            "Economic_Activity": {
                "Volume": 1391133.0,
                "TVL": 0,
                "Fees": 0
            },
            "Supply": {
                "Circulating": 462277841.3255647,
                "Total": 552473209.5478008,
                "Locked_Pct": 16.325745151708084
            }
        },
        "Quality_Scores": {
            "Predictability": 7,
            "Profitability": 5,
            "Growth": 6,
            "Moat": 4,
            "Financial_Strength": 9,
            "Valuation": 7
        },
        "10_Year_History": {},
        "Last_Updated": "2026-03-09 18:32"
    },
    "W": {
        "Name": "Wormhole",
        "Current_Price": 0.01837932,
        "Market_Cap": 101566948.0,
        "Financial_Tab_Data": {
            "Economic_Activity": {
                "Volume": 16182598.0,
                "TVL": 1325347474.437528,
                "Fees": 0
            },
            "Supply": {
                "Circulating": 5527330127.0,
                "Total": 10000000000.0,
                "Locked_Pct": 44.72669873
            }
        },
        "Quality_Scores": {
            "Predictability": 7,
            "Profitability": 5,
            "Growth": 9,
            "Moat": 8,
            "Financial_Strength": 5,
            "Valuation": 7
        },
        "10_Year_History": {},
        "Last_Updated": "2026-03-09 18:33"
    },
    "WMTX": {
        "Name": "World Mobile Token",
        "Current_Price": 0.065913,
        "Market_Cap": 54906993.0,
        "Financial_Tab_Data": {
            "Economic_Activity": {
                "Volume": 6002640.0,
                "TVL": 0,
                "Fees": 0
            },
            "Supply": {
                "Circulating": 833403824.728708,
                "Total": 2000000000.0,
                "Locked_Pct": 58.32980876356459
            }
        },
        "Quality_Scores": {
            "Predictability": 7,
            "Profitability": 5,
            "Growth": 9,
            "Moat": 4,
            "Financial_Strength": 5,
            "Valuation": 7
        },
        "10_Year_History": {},
        "Last_Updated": "2026-03-09 18:34"
    },
    "WAVES": {
        "Name": "Waves",
        "Current_Price": 0.452478,
        "Market_Cap": 45242869.0,
        "Financial_Tab_Data": {
            "Economic_Activity": {
                "Volume": 1482119.0,
                "TVL": 0,
                "Fees": 0
            },
            "Supply": {
                "Circulating": 100000000.0,
                "Total": 100000000.0,
                "Locked_Pct": 0
            }
        },
        "Quality_Scores": {
            "Predictability": 7,
            "Profitability": 5,
            "Growth": 6,
            "Moat": 4,
            "Financial_Strength": 9,
            "Valuation": 7
        },
        "10_Year_History": {},
        "Last_Updated": "2026-03-09 18:35"
    },
    "WOULD": {
        "Name": "would",
        "Current_Price": 0.04360405,
        "Market_Cap": 43359779.0,
        "Financial_Tab_Data": {
            "Economic_Activity": {
                "Volume": 8818.7,
                "TVL": 0,
                "Fees": 0
            },
            "Supply": {
                "Circulating": 999452576.553828,
                "Total": 999452576.553828,
                "Locked_Pct": 0
            }
        },
        "Quality_Scores": {
            "Predictability": 7,
            "Profitability": 5,
            "Growth": 6,
            "Moat": 4,
            "Financial_Strength": 9,
            "Valuation": 7
        },
        "10_Year_History": {},
        "Last_Updated": "2026-03-09 18:35"
    },
    "WHITEWHALE": {
        "Name": "The White Whale",
        "Current_Price": 0.04280309,
        "Market_Cap": 42772692.0,
        "Financial_Tab_Data": {
            "Economic_Activity": {
                "Volume": 2016270.0,
                "TVL": 0,
                "Fees": 0
            },
            "Supply": {
                "Circulating": 1000000000.0,
                "Total": 1000000000.0,
                "Locked_Pct": 0
            }
        },
        "Quality_Scores": {
            "Predictability": 7,
            "Profitability": 5,
            "Growth": 6,
            "Moat": 4,
            "Financial_Strength": 9,
            "Valuation": 7
        },
        "10_Year_History": {},
        "Last_Updated": "2026-03-09 18:35"
    }
}